{
    "partname": "optimization",
    "runtime": 293.9325575940311,
    "results": {
        "CONF1": {
            "xtb_opt": {
                "energy": -389.3841113,
                "grad_norm": 0.000360469819,
                "converged": true,
                "geom": [
                    {
                        "element": "C",
                        "xyz": [
                            -3.659006190038434,
                            -0.23516133486215446,
                            0.005741829871067284
                        ]
                    },
                    {
                        "element": "C",
                        "xyz": [
                            -2.1638973927935012,
                            -0.06966951725546121,
                            -0.0052137518431211805
                        ]
                    },
                    {
                        "element": "C",
                        "xyz": [
                            -1.5691166338736064,
                            1.190583239029956,
                            -0.0006902889577472325
                        ]
                    },
                    {
                        "element": "C",
                        "xyz": [
                            -0.18304921458005716,
                            1.3308166321323438,
                            0.0031962130184217483
                        ]
                    },
                    {
                        "element": "C",
                        "xyz": [
                            0.6561278218262957,
                            0.21821553025995488,
                            0.0020138132279713386
                        ]
                    },
                    {
                        "element": "C",
                        "xyz": [
                            0.05808694570192078,
                            -1.0466727859263383,
                            -0.0037813900572596323
                        ]
                    },
                    {
                        "element": "C",
                        "xyz": [
                            -1.3226445079114977,
                            -1.187022698374209,
                            -0.007967850104968038
                        ]
                    },
                    {
                        "element": "C",
                        "xyz": [
                            2.1630079094374133,
                            0.37454446941892333,
                            0.0034601755415567606
                        ]
                    },
                    {
                        "element": "C",
                        "xyz": [
                            2.791696493031011,
                            -0.22078777634129237,
                            -1.2631508392714177
                        ]
                    },
                    {
                        "element": "C",
                        "xyz": [
                            2.791580981017964,
                            -0.23514215977597563,
                            1.263229555245355
                        ]
                    },
                    {
                        "element": "H",
                        "xyz": [
                            -4.165698561062364,
                            0.7217720044955733,
                            -0.14110680042100668
                        ]
                    },
                    {
                        "element": "H",
                        "xyz": [
                            -3.987133013194406,
                            -0.9190538954699804,
                            -0.7836945700134418
                        ]
                    },
                    {
                        "element": "H",
                        "xyz": [
                            -4.001002149131757,
                            -0.652913970053199,
                            0.959458837849031
                        ]
                    },
                    {
                        "element": "H",
                        "xyz": [
                            -2.196766341786971,
                            2.077823149578701,
                            -0.000989755445677009
                        ]
                    },
                    {
                        "element": "H",
                        "xyz": [
                            0.2530062451634607,
                            2.326592700949213,
                            0.005332731351226107
                        ]
                    },
                    {
                        "element": "H",
                        "xyz": [
                            0.6799078575970627,
                            -1.9376184644144208,
                            -0.007207494840285497
                        ]
                    },
                    {
                        "element": "H",
                        "xyz": [
                            -1.7596867328512886,
                            -2.182479453940178,
                            -0.013998508866342253
                        ]
                    },
                    {
                        "element": "H",
                        "xyz": [
                            2.3760232282279947,
                            1.4516651805124865,
                            0.009586558679121296
                        ]
                    },
                    {
                        "element": "H",
                        "xyz": [
                            2.6306253052956152,
                            -1.303086939585624,
                            -1.308099464786039
                        ]
                    },
                    {
                        "element": "H",
                        "xyz": [
                            3.8721733654568644,
                            -0.042878866103520076,
                            -1.2781329052623986
                        ]
                    },
                    {
                        "element": "H",
                        "xyz": [
                            2.3548471581035186,
                            0.2210856550703932,
                            -2.1634500984681377
                        ]
                    },
                    {
                        "element": "H",
                        "xyz": [
                            2.3549315799276656,
                            0.19655996147398308,
                            2.1685424356573786
                        ]
                    },
                    {
                        "element": "H",
                        "xyz": [
                            3.8720613339424044,
                            -0.057434520209665225,
                            1.2800604193873926
                        ]
                    },
                    {
                        "element": "H",
                        "xyz": [
                            2.6306893606063295,
                            -1.3179006406380915,
                            1.2960163481699483
                        ]
                    }
                ],
                "cycles": 4,
                "ecyc": [
                    -389.3840088,
                    -389.3841007,
                    -389.3841091,
                    -389.3841113
                ],
                "gncyc": [
                    0.020355764847,
                    0.0052009,
                    0.0011348,
                    0.0006161,
                    0.0004697,
                    0.000360469819
                ]
            },
            "xtb_rrho": {
                "energy": 0.169633189054,
                "rmsd": null,
                "gibbs": {
                    "298.15": 0.169633189054
                },
                "enthalpy": {
                    "298.15": null
                },
                "entropy": {
                    "298.15": null
                },
                "symmetry": "c1",
                "symnum": 1,
                "linear": false
            },
            "gtot": -389.21447811094595,
            "bmw": 0.9808292564686575
        },
        "CONF2": {
            "xtb_opt": {
                "energy": -389.3802349,
                "grad_norm": 0.000233200643,
                "converged": true,
                "geom": [
                    {
                        "element": "C",
                        "xyz": [
                            -3.680327018838437,
                            -0.1665352116000595,
                            -0.11971791238517686
                        ]
                    },
                    {
                        "element": "C",
                        "xyz": [
                            -2.1837922515714534,
                            -0.0670698794683137,
                            -0.008941414575197435
                        ]
                    },
                    {
                        "element": "C",
                        "xyz": [
                            -1.4900419323321927,
                            0.997359895836737,
                            -0.5873816787148192
                        ]
                    },
                    {
                        "element": "C",
                        "xyz": [
                            -0.10531656318410855,
                            1.0834071724388876,
                            -0.5108804361641001
                        ]
                    },
                    {
                        "element": "C",
                        "xyz": [
                            0.654280010511736,
                            0.11020289116043523,
                            0.14982864738914706
                        ]
                    },
                    {
                        "element": "C",
                        "xyz": [
                            -0.04659376188702374,
                            -0.9506913251976588,
                            0.7308182746986053
                        ]
                    },
                    {
                        "element": "C",
                        "xyz": [
                            -1.4337406586922816,
                            -1.036390296393802,
                            0.6541551972671645
                        ]
                    },
                    {
                        "element": "C",
                        "xyz": [
                            2.1708717767298498,
                            0.227195332147786,
                            0.26792253398319693
                        ]
                    },
                    {
                        "element": "C",
                        "xyz": [
                            2.801486303647165,
                            0.9851805561564836,
                            -0.9070066423606685
                        ]
                    },
                    {
                        "element": "C",
                        "xyz": [
                            2.8616734457253457,
                            -1.1332118924549892,
                            0.42408028776255824
                        ]
                    },
                    {
                        "element": "H",
                        "xyz": [
                            -4.161117072768374,
                            0.781335798043858,
                            0.142237181310117
                        ]
                    },
                    {
                        "element": "H",
                        "xyz": [
                            -3.98231073990439,
                            -0.4116465658246571,
                            -1.1445054498020042
                        ]
                    },
                    {
                        "element": "H",
                        "xyz": [
                            -4.076558260643699,
                            -0.9432289648431268,
                            0.5391606585643764
                        ]
                    },
                    {
                        "element": "H",
                        "xyz": [
                            -2.0430584821800037,
                            1.7733656775865938,
                            -1.1111531249675415
                        ]
                    },
                    {
                        "element": "H",
                        "xyz": [
                            0.3838866354570961,
                            1.9303011728161952,
                            -0.9783008981453524
                        ]
                    },
                    {
                        "element": "H",
                        "xyz": [
                            0.48780612937459844,
                            -1.7327257427330691,
                            1.2577360316845294
                        ]
                    },
                    {
                        "element": "H",
                        "xyz": [
                            -1.9403409582392885,
                            -1.878339470745187,
                            1.1188544167419958
                        ]
                    },
                    {
                        "element": "H",
                        "xyz": [
                            2.377090741249233,
                            0.8068082085965872,
                            1.1810095595701364
                        ]
                    },
                    {
                        "element": "H",
                        "xyz": [
                            2.472490418904128,
                            2.0257638152255892,
                            -0.9599300096040991
                        ]
                    },
                    {
                        "element": "H",
                        "xyz": [
                            2.554247168959631,
                            0.500203858240089,
                            -1.8578579614616324
                        ]
                    },
                    {
                        "element": "H",
                        "xyz": [
                            3.8905537524811726,
                            0.9959560141150631,
                            -0.8026687842420053
                        ]
                    },
                    {
                        "element": "H",
                        "xyz": [
                            3.947198887165055,
                            -1.0000494445911357,
                            0.452972713600748
                        ]
                    },
                    {
                        "element": "H",
                        "xyz": [
                            2.620288453328642,
                            -1.7884944941321628,
                            -0.420170755579724
                        ]
                    },
                    {
                        "element": "H",
                        "xyz": [
                            2.5746439808979544,
                            -1.6452773159963197,
                            1.3455362370666468
                        ]
                    }
                ],
                "cycles": 6,
                "ecyc": [
                    -389.3800712,
                    -389.3801731,
                    -389.3801944,
                    -389.3802206,
                    -389.3802301,
                    -389.3802349
                ],
                "gncyc": [
                    0.019376682825,
                    0.0050676,
                    0.0013882,
                    0.0011095,
                    0.0012972,
                    0.0007199,
                    0.0002187,
                    0.000233200643
                ]
            },
            "xtb_rrho": {
                "energy": 0.169472164597,
                "rmsd": null,
                "gibbs": {
                    "298.15": 0.169472164597
                },
                "enthalpy": {
                    "298.15": null
                },
                "entropy": {
                    "298.15": null
                },
                "symmetry": "c1",
                "symnum": 1,
                "linear": false
            },
            "gtot": -389.210762735403,
            "bmw": 0.019170743531342474
        }
    },
    "settings": {
        "optcycles": 8,
        "maxcyc": 200,
        "threshold": 1.5,
        "hlow": 0.01,
        "gradthr": 0.01,
        "func": "r2scan-3c",
        "basis": "def2-tzvp",
        "prog": "orca",
        "sm": "smd",
        "gfnv": "gfn2",
        "optlevel": "normal",
        "run": true,
        "macrocycles": true,
        "crestcheck": true,
        "template": false,
        "constrain": false,
        "xtb_opt": true
    },
    "nconf_in": 2,
    "nconf_out": 2
}