{
    "partname": "optimization",
    "runtime": 183.23853973997757,
    "results": {
        "CONF1": {
            "xtb_opt": {
                "energy": -384.7925019,
                "grad_norm": 0.000639856204,
                "converged": true,
                "geom": [
                    {
                        "element": "C",
                        "xyz": [
                            -1.0924569481593913,
                            -1.9153524938229913,
                            -0.00015633562433732304
                        ]
                    },
                    {
                        "element": "C",
                        "xyz": [
                            -0.019829189180597076,
                            -0.8670094505680651,
                            -1.3420890238184931e-05
                        ]
                    },
                    {
                        "element": "C",
                        "xyz": [
                            1.3224523907916519,
                            -1.2476830859509684,
                            0.00017087652803750487
                        ]
                    },
                    {
                        "element": "C",
                        "xyz": [
                            2.352170128942008,
                            -0.3105481960760861,
                            0.00021775576540770177
                        ]
                    },
                    {
                        "element": "C",
                        "xyz": [
                            2.064632629116689,
                            1.0509498082028874,
                            -7.171123903849748e-06
                        ]
                    },
                    {
                        "element": "C",
                        "xyz": [
                            0.738400972907526,
                            1.4531055646256663,
                            -0.00033264848914426904
                        ]
                    },
                    {
                        "element": "C",
                        "xyz": [
                            -0.3053680242126323,
                            0.5182706451185518,
                            -0.00037881905155254497
                        ]
                    },
                    {
                        "element": "C",
                        "xyz": [
                            -1.6728784472538893,
                            1.0659961884444853,
                            -0.0012933015893866048
                        ]
                    },
                    {
                        "element": "O",
                        "xyz": [
                            -2.7076476831158973,
                            0.4295256771611871,
                            0.00016767752189658303
                        ]
                    },
                    {
                        "element": "H",
                        "xyz": [
                            -1.7457585411789673,
                            -1.8147062426299188,
                            0.8712522192559021
                        ]
                    },
                    {
                        "element": "H",
                        "xyz": [
                            -1.745922604504596,
                            -1.814315940539672,
                            -0.8713968899256287
                        ]
                    },
                    {
                        "element": "H",
                        "xyz": [
                            -0.6456454007699742,
                            -2.9127121900035213,
                            -0.0004234147551704874
                        ]
                    },
                    {
                        "element": "H",
                        "xyz": [
                            1.5653223983248215,
                            -2.3065163234233648,
                            0.0002565830972848137
                        ]
                    },
                    {
                        "element": "H",
                        "xyz": [
                            3.3840936609509624,
                            -0.6479178867465543,
                            0.00041552407142054056
                        ]
                    },
                    {
                        "element": "H",
                        "xyz": [
                            2.8640941582132897,
                            1.7840376132503155,
                            3.0759822720828016e-05
                        ]
                    },
                    {
                        "element": "H",
                        "xyz": [
                            0.48972257266401037,
                            2.51170298846122,
                            -0.0005008190124961685
                        ]
                    },
                    {
                        "element": "H",
                        "xyz": [
                            -1.7005120969431313,
                            2.1818795935793998,
                            0.00024345941810405855
                        ]
                    }
                ],
                "cycles": 3,
                "ecyc": [
                    -384.7924254,
                    -384.7924983,
                    -384.7925019
                ],
                "gncyc": [
                    0.024443866978,
                    0.0048198,
                    0.0014259,
                    0.0006536,
                    0.000639856204
                ]
            },
            "xtb_rrho": {
                "energy": 0.10078592991,
                "rmsd": null,
                "gibbs": {
                    "298.15": 0.10078592991
                },
                "enthalpy": {
                    "298.15": null
                },
                "entropy": {
                    "298.15": null
                },
                "symmetry": "c1",
                "symnum": 1,
                "linear": false
            },
            "gtot": -384.69171597009,
            "bmw": 0.8340233230739479
        },
        "CONF2": {
            "xtb_opt": {
                "energy": -384.7906824,
                "grad_norm": 0.000250066941,
                "converged": true,
                "geom": [
                    {
                        "element": "C",
                        "xyz": [
                            -0.828262943622721,
                            -2.292285253510181,
                            0.00014178674288851565
                        ]
                    },
                    {
                        "element": "C",
                        "xyz": [
                            0.07041660517942583,
                            -1.0823121761974301,
                            5.049154384574302e-05
                        ]
                    },
                    {
                        "element": "C",
                        "xyz": [
                            1.45554348295114,
                            -1.2561785967432217,
                            -0.00024966339718444496
                        ]
                    },
                    {
                        "element": "C",
                        "xyz": [
                            2.322231560319285,
                            -0.16846467390636943,
                            -0.00024345328420992236
                        ]
                    },
                    {
                        "element": "C",
                        "xyz": [
                            1.820024194798652,
                            1.1316080065312417,
                            4.605956603839228e-05
                        ]
                    },
                    {
                        "element": "C",
                        "xyz": [
                            0.44958279440817295,
                            1.327155722652017,
                            0.00026353216730776136
                        ]
                    },
                    {
                        "element": "C",
                        "xyz": [
                            -0.42934102133075797,
                            0.2365731280610518,
                            0.0002547328201505264
                        ]
                    },
                    {
                        "element": "C",
                        "xyz": [
                            -1.8802483813204465,
                            0.5132940886096653,
                            0.0004047471556465333
                        ]
                    },
                    {
                        "element": "O",
                        "xyz": [
                            -2.3620856336141256,
                            1.6293678012637411,
                            6.0679378575146315e-05
                        ]
                    },
                    {
                        "element": "H",
                        "xyz": [
                            -1.4760108342292195,
                            -2.318978457276319,
                            -0.8819328626791283
                        ]
                    },
                    {
                        "element": "H",
                        "xyz": [
                            -0.2290595713426675,
                            -3.205377104797246,
                            -0.00032761749062976386
                        ]
                    },
                    {
                        "element": "H",
                        "xyz": [
                            -1.475212017322884,
                            -2.319383551957997,
                            0.8827993527699839
                        ]
                    },
                    {
                        "element": "H",
                        "xyz": [
                            1.8613493596759327,
                            -2.2637297632817615,
                            -0.00048532472628424117
                        ]
                    },
                    {
                        "element": "H",
                        "xyz": [
                            3.3946013574002456,
                            -0.33743314653255035,
                            -0.00046728690848048835
                        ]
                    },
                    {
                        "element": "H",
                        "xyz": [
                            2.4958269883725666,
                            1.9803436052721202,
                            8.694216312969448e-05
                        ]
                    },
                    {
                        "element": "H",
                        "xyz": [
                            0.0200901931328817,
                            2.32374606241121,
                            0.0004328410097848614
                        ]
                    },
                    {
                        "element": "H",
                        "xyz": [
                            -2.5445302848113838,
                            -0.3762076084029275,
                            0.0011947226378018255
                        ]
                    }
                ],
                "cycles": 4,
                "ecyc": [
                    -384.7906399,
                    -384.7906815,
                    -384.790679,
                    -384.7906824
                ],
                "gncyc": [
                    0.023837647666,
                    0.0047073,
                    0.0008429,
                    0.0012824,
                    0.0002492,
                    0.000250066941
                ]
            },
            "xtb_rrho": {
                "energy": 0.100490733526,
                "rmsd": null,
                "gibbs": {
                    "298.15": 0.100490733526
                },
                "enthalpy": {
                    "298.15": null
                },
                "entropy": {
                    "298.15": null
                },
                "symmetry": "c1",
                "symnum": 1,
                "linear": false
            },
            "gtot": -384.690191666474,
            "bmw": 0.16597667692605206
        }
    },
    "settings": {
        "optcycles": 8,
        "maxcyc": 200,
        "threshold": 1.5,
        "hlow": 0.01,
        "gradthr": 0.01,
        "func": "r2scan-3c",
        "basis": "def2-tzvp",
        "prog": "orca",
        "sm": "smd",
        "gfnv": "gfn2",
        "optlevel": "normal",
        "run": true,
        "macrocycles": true,
        "crestcheck": true,
        "template": false,
        "constrain": false,
        "xtb_opt": true
    },
    "nconf_in": 2,
    "nconf_out": 2
}