{
    "partname": "optimization",
    "runtime": 655.896426339983,
    "results": {
        "CONF1": {
            "xtb_opt": {
                "energy": -196.4608871,
                "grad_norm": 0.000486150783,
                "converged": true,
                "geom": [
                    {
                        "element": "C",
                        "xyz": [
                            1.2014992029785745,
                            1.2613530220505402,
                            -0.03422739958140217
                        ]
                    },
                    {
                        "element": "C",
                        "xyz": [
                            0.3996410464049403,
                            -3.6488049760805814e-05,
                            0.31454651693211455
                        ]
                    },
                    {
                        "element": "C",
                        "xyz": [
                            1.2004381558592814,
                            -1.2620356909032333,
                            -0.03451186404947939
                        ]
                    },
                    {
                        "element": "C",
                        "xyz": [
                            -0.9161848736217872,
                            0.000575445142410012,
                            -0.4074916573955545
                        ]
                    },
                    {
                        "element": "C",
                        "xyz": [
                            -2.113321761663882,
                            0.00023216626738634295,
                            0.1712919441881705
                        ]
                    },
                    {
                        "element": "H",
                        "xyz": [
                            0.6473410766246083,
                            2.167108109814287,
                            0.22863881382771947
                        ]
                    },
                    {
                        "element": "H",
                        "xyz": [
                            1.4152777259881328,
                            1.2948312938867634,
                            -1.1089735892713557
                        ]
                    },
                    {
                        "element": "H",
                        "xyz": [
                            2.158494028501268,
                            1.2728722936998838,
                            0.4982108108416689
                        ]
                    },
                    {
                        "element": "H",
                        "xyz": [
                            0.19814733883034114,
                            -8.867416688722683e-05,
                            1.3941628514254483
                        ]
                    },
                    {
                        "element": "H",
                        "xyz": [
                            1.4140415549374392,
                            -1.2955448049503009,
                            -1.1092904631930278
                        ]
                    },
                    {
                        "element": "H",
                        "xyz": [
                            2.157489238611606,
                            -1.2744067976296038,
                            0.4978075942967871
                        ]
                    },
                    {
                        "element": "H",
                        "xyz": [
                            0.645549415507932,
                            -2.167356572538194,
                            0.22830217932354976
                        ]
                    },
                    {
                        "element": "H",
                        "xyz": [
                            -0.8485595521693207,
                            0.0012412191044306672,
                            -1.4978025018907666
                        ]
                    },
                    {
                        "element": "H",
                        "xyz": [
                            -3.028979156906866,
                            0.0006212641174316028,
                            -0.4114063833106803
                        ]
                    },
                    {
                        "element": "H",
                        "xyz": [
                            -2.215331731203795,
                            -0.00043827624970223917,
                            1.253974602918005
                        ]
                    }
                ],
                "cycles": 3,
                "ecyc": [
                    -196.4608413,
                    -196.4608835,
                    -196.4608871
                ],
                "gncyc": [
                    0.021836165601,
                    0.005108,
                    0.0008946,
                    0.0004756,
                    0.000486150783
                ]
            },
            "xtb_rrho": {
                "energy": 0.10477082006,
                "rmsd": null,
                "gibbs": {
                    "298.15": 0.10477082006
                },
                "enthalpy": {
                    "298.15": null
                },
                "entropy": {
                    "298.15": null
                },
                "symmetry": "c1",
                "symnum": 1,
                "linear": false
            },
            "gtot": -196.35611627994,
            "bmw": 0.6296453442869907
        },
        "CONF2": {
            "xtb_opt": {
                "energy": -196.4602859,
                "grad_norm": 0.000869472414,
                "converged": true,
                "geom": [
                    {
                        "element": "C",
                        "xyz": [
                            1.2877454573236182,
                            1.2209918827985857,
                            -0.24100020893938442
                        ]
                    },
                    {
                        "element": "C",
                        "xyz": [
                            0.4813373400179776,
                            0.09745824231510843,
                            0.4317478488548565
                        ]
                    },
                    {
                        "element": "C",
                        "xyz": [
                            0.9091358509506778,
                            -1.269521418013945,
                            -0.09527212309461602
                        ]
                    },
                    {
                        "element": "C",
                        "xyz": [
                            -0.9894916980527392,
                            0.37658391107149414,
                            0.2842126116796419
                        ]
                    },
                    {
                        "element": "C",
                        "xyz": [
                            -1.896826894931391,
                            -0.4006460022800727,
                            -0.3015526569341527
                        ]
                    },
                    {
                        "element": "H",
                        "xyz": [
                            1.013031155071826,
                            2.2033164094890045,
                            0.15663703977067953
                        ]
                    },
                    {
                        "element": "H",
                        "xyz": [
                            1.096981521238635,
                            1.2286523221854746,
                            -1.3197014919675005
                        ]
                    },
                    {
                        "element": "H",
                        "xyz": [
                            2.361705179398758,
                            1.0783931775004654,
                            -0.08253150133324466
                        ]
                    },
                    {
                        "element": "H",
                        "xyz": [
                            0.7063504437030856,
                            0.13585184630743422,
                            1.5092825887952774
                        ]
                    },
                    {
                        "element": "H",
                        "xyz": [
                            0.36419312733449777,
                            -2.080352883381684,
                            0.397964502998407
                        ]
                    },
                    {
                        "element": "H",
                        "xyz": [
                            0.7314402824851226,
                            -1.3452866349447066,
                            -1.1740532224617921
                        ]
                    },
                    {
                        "element": "H",
                        "xyz": [
                            1.9783263382602578,
                            -1.4250735170051592,
                            0.077835388925067
                        ]
                    },
                    {
                        "element": "H",
                        "xyz": [
                            -1.3119343863933772,
                            1.3355202253157195,
                            0.6932437899411712
                        ]
                    },
                    {
                        "element": "H",
                        "xyz": [
                            -2.9347083721879477,
                            -0.09135393245164858,
                            -0.3728887973566334
                        ]
                    },
                    {
                        "element": "H",
                        "xyz": [
                            -1.6418886353804985,
                            -1.3627566614787534,
                            -0.7352678269876667
                        ]
                    }
                ],
                "cycles": 3,
                "ecyc": [
                    -196.46024,
                    -196.4602813,
                    -196.4602859
                ],
                "gncyc": [
                    0.022746374958,
                    0.0055637,
                    0.0011773,
                    0.0008622,
                    0.000869472414
                ]
            },
            "xtb_rrho": {
                "energy": 0.105329159938,
                "rmsd": null,
                "gibbs": {
                    "298.15": 0.105329159938
                },
                "enthalpy": {
                    "298.15": null
                },
                "entropy": {
                    "298.15": null
                },
                "symmetry": "c1",
                "symnum": 1,
                "linear": false
            },
            "gtot": -196.354956740062,
            "bmw": 0.18439306005197248
        },
        "CONF3": {
            "xtb_opt": {
                "energy": -196.4602982,
                "grad_norm": 0.000786689632,
                "converged": true,
                "geom": [
                    {
                        "element": "C",
                        "xyz": [
                            1.211123180340555,
                            1.3139541965374768,
                            -0.02779332445643436
                        ]
                    },
                    {
                        "element": "C",
                        "xyz": [
                            0.4881778835136062,
                            0.028537919802449966,
                            0.40726767398153074
                        ]
                    },
                    {
                        "element": "C",
                        "xyz": [
                            0.9536656828423987,
                            -1.165449211047545,
                            -0.4214901746774972
                        ]
                    },
                    {
                        "element": "C",
                        "xyz": [
                            -0.9987906855570966,
                            0.25227652446014665,
                            0.3738804369521044
                        ]
                    },
                    {
                        "element": "C",
                        "xyz": [
                            -1.8975584107483163,
                            -0.4389120658636519,
                            -0.3220579508130326
                        ]
                    },
                    {
                        "element": "H",
                        "xyz": [
                            2.2956645903448627,
                            1.2026123677362244,
                            0.07039311456308625
                        ]
                    },
                    {
                        "element": "H",
                        "xyz": [
                            0.9008720430083939,
                            2.1708556118644817,
                            0.578442282115607
                        ]
                    },
                    {
                        "element": "H",
                        "xyz": [
                            0.9818514189034777,
                            1.5407000221393479,
                            -1.0744538322755128
                        ]
                    },
                    {
                        "element": "H",
                        "xyz": [
                            0.7587817673082856,
                            -0.15687670355268937,
                            1.458691132673641
                        ]
                    },
                    {
                        "element": "H",
                        "xyz": [
                            0.7240024601461449,
                            -1.0161969723953235,
                            -1.4822932355086982
                        ]
                    },
                    {
                        "element": "H",
                        "xyz": [
                            2.0363402316936354,
                            -1.292951542539483,
                            -0.3289289144932084
                        ]
                    },
                    {
                        "element": "H",
                        "xyz": [
                            0.47436678392758186,
                            -2.093480174148572,
                            -0.09544617545154171
                        ]
                    },
                    {
                        "element": "H",
                        "xyz": [
                            -1.3444147799615032,
                            1.0872274789196803,
                            0.9843762001844817
                        ]
                    },
                    {
                        "element": "H",
                        "xyz": [
                            -2.9509064670580356,
                            -0.18161470327520166,
                            -0.2838595293391687
                        ]
                    },
                    {
                        "element": "H",
                        "xyz": [
                            -1.6214561888456993,
                            -1.277896805015416,
                            -0.9519849617256545
                        ]
                    }
                ],
                "cycles": 29,
                "ecyc": [
                    -196.4565507,
                    -196.4566064,
                    -196.4566252,
                    -196.4566632,
                    -196.4567336,
                    -196.4553163,
                    -196.4568006,
                    -196.4568622,
                    -196.4569451,
                    -196.4571509,
                    -196.4573265,
                    -196.457502,
                    -196.4579075,
                    -196.4584055,
                    -196.4582271,
                    -196.4588195,
                    -196.4590031,
                    -196.4594857,
                    -196.4586358,
                    -196.4598031,
                    -196.459975,
                    -196.4591153,
                    -196.4601183,
                    -196.4602062,
                    -196.4602283,
                    -196.4602543,
                    -196.4602788,
                    -196.4602952,
                    -196.4602982
                ],
                "gncyc": [
                    0.021155361556,
                    0.0046966,
                    0.0010178,
                    0.0013791,
                    0.0021868,
                    0.0039505,
                    0.034931,
                    0.0030476,
                    0.0029629,
                    0.002962648267,
                    0.002961830292,
                    0.0016512,
                    0.0079786,
                    0.0051481,
                    0.0304143,
                    0.0165858,
                    0.0066833,
                    0.027042,
                    0.0061343,
                    0.006155152775,
                    0.006152622926,
                    0.0023396,
                    0.004203,
                    0.0304032,
                    0.0059517,
                    0.003028,
                    0.0281183,
                    0.0012936,
                    0.0029158,
                    0.002916885484,
                    0.00291552897,
                    0.000844,
                    0.0027712,
                    0.0023251,
                    0.0015341,
                    0.0007988,
                    0.000786689632
                ]
            },
            "xtb_rrho": {
                "energy": 0.105333462227,
                "rmsd": null,
                "gibbs": {
                    "298.15": 0.105333462227
                },
                "enthalpy": {
                    "298.15": null
                },
                "entropy": {
                    "298.15": null
                },
                "symmetry": "c1",
                "symnum": 1,
                "linear": false
            },
            "gtot": -196.354964737773,
            "bmw": 0.18596159566103684
        }
    },
    "settings": {
        "optcycles": 8,
        "maxcyc": 200,
        "threshold": 1.5,
        "hlow": 0.01,
        "gradthr": 0.01,
        "func": "r2scan-3c",
        "basis": "def2-tzvp",
        "prog": "orca",
        "sm": "smd",
        "gfnv": "gfn2",
        "optlevel": "normal",
        "run": true,
        "macrocycles": true,
        "crestcheck": true,
        "template": false,
        "constrain": false,
        "xtb_opt": true
    },
    "nconf_in": 3,
    "nconf_out": 3
}